<?xml version="1.0" encoding="utf-8" ?>
<dwsync>
<file name="modernizr.custom.79639.js" server="blackhawk.cs.mercer.edu//www/Old Folders/Boakai Mamey/Research/" local="130375755000000000" remote="130375755000000000" Dst="1" />
<file name="jquery.ba-cond.min.js" server="blackhawk.cs.mercer.edu//www/Old Folders/Boakai Mamey/Research/" local="130375755000000000" remote="130375755000000000" Dst="1" />
<file name="jquery.slitslider.js" server="blackhawk.cs.mercer.edu//www/Old Folders/Boakai Mamey/Research/" local="130375755000000000" remote="130375755000000000" Dst="1" />
<file name="modernizr.custom.79639.js" server="C:/Program Files (x86)/Zend/Apache2/htdocs" local="130417381094285399" remote="130417381090000000" Dst="2" />
<file name="jquery.ba-cond.min.js" server="C:/Program Files (x86)/Zend/Apache2/htdocs" local="130417381097342215" remote="130417381090000000" Dst="2" />
<file name="jquery.slitslider.js" server="C:/Program Files (x86)/Zend/Apache2/htdocs" local="130417381098132743" remote="130417381090000000" Dst="2" />
<file name="modernizr.custom.79639.js" server="C:/Program Files (x86)/Zend/Apache2/htdocs/" local="130420195988793461" remote="130420195980000000" Dst="2" />
<file name="jquery.ba-cond.min.js" server="C:/Program Files (x86)/Zend/Apache2/htdocs/" local="130420195991664823" remote="130420195990000000" Dst="2" />
<file name="jquery.slitslider.js" server="C:/Program Files (x86)/Zend/Apache2/htdocs/" local="130420195991894975" remote="130420195990000000" Dst="2" />
</dwsync>